MetaDetective/MetaDetective.py
MetaDetective-1.0.9.dist-info/LICENSE
MetaDetective-1.0.9.dist-info/METADATA
MetaDetective-1.0.9.dist-info/WHEEL
MetaDetective-1.0.9.dist-info/entry_points.txt
MetaDetective-1.0.9.dist-info/top_level.txt
MetaDetective-1.0.9.dist-info/RECORD
