Metadata-Version: 2.1
Name: MetaDetective
Version: 1.0.9
Summary: Unleash Metadata Intelligence with MetaDetective. Your Assistant Beyond Metagoofil.
Author-email: Franck Ferman <contact@franckferman.fr>
License: GNU AFFERO GENERAL PUBLIC LICENSE
Project-URL: Homepage, https://github.com/franckferman/MetaDetective
Keywords: metadata,osint,cyber-security
Classifier: Programming Language :: Python :: 3
Classifier: License :: OSI Approved :: GNU Affero General Public License v3
Classifier: Operating System :: POSIX :: Linux
Classifier: Topic :: Security
Classifier: Topic :: Utilities
Requires-Python: >=3.9
License-File: LICENSE
